Metadata-Version: 1.1
Name: flask-resty-shared-session
Version: 0.1.2
Summary: An adapted flask-session module and corresponding OpenResty package, so flask and Nginx can share session information.
Home-page: https://github.com/scivey/flask-resty-shared-session
Author: Scott Ivey
Author-email: scott.ivey@gmail.com
License: BSD
Platform: any
Classifier: Environment :: Web Environment
Classifier: Intended Audience :: Developers
Classifier: License :: OSI Approved :: BSD License
Classifier: Operating System :: OS Independent
Classifier: Programming Language :: Python :: 2
Classifier: Topic :: Internet :: WWW/HTTP :: Dynamic Content
Classifier: Topic :: Software Development :: Libraries :: Python Modules
